properties/p.py
property-2.6.2.dist-info/LICENSE.txt
property-2.6.2.dist-info/METADATA
property-2.6.2.dist-info/WHEEL
property-2.6.2.dist-info/top_level.txt
property-2.6.2.dist-info/RECORD
