Metadata-Version: 2.1
Name: property
Version: 2.6.2
Summary:  A python module to load property files. Recursively define properties, load from env.
Home-page: https://github.com/anandjoshi91/pythonpropertyfileloader
Download-URL: https://github.com/anandjoshi91/pythonpropertyfileloader/archive/refs/tags/2.6.2.zip
Author: Anand Joshi
Author-email: anandhjoshi@outlook.com
License: MIT
Keywords: property,read-property-file,property-interpolation
Classifier: License :: OSI Approved :: MIT License
Classifier: Programming Language :: Python :: 3
Classifier: Programming Language :: Python :: 3.7
Classifier: Programming Language :: Python :: 3.8
Classifier: Programming Language :: Python :: 3.9
Classifier: Programming Language :: Python :: 3.10
License-File: LICENSE.txt
